neocities/__init__.py
neocities/__main__.py
neocities/cli.py
neocities/errors.py
neocities/neocities.py
neocities_neo-0.0.2.dist-info/licenses/LICENSE
neocities_neo-0.0.2.dist-info/METADATA
neocities_neo-0.0.2.dist-info/WHEEL
neocities_neo-0.0.2.dist-info/entry_points.txt
neocities_neo-0.0.2.dist-info/top_level.txt
neocities_neo-0.0.2.dist-info/RECORD
