Metadata-Version: 2.4
Name: neocities-neo
Version: 0.0.2
Summary: An api for neocities.org
Author-email: Dominik Stanisław Suchora <hexderm@gmail.com>
License: GPLv3
Project-URL: Homepage, https://github.com/TUVIMEN/neocities
Keywords: api,cli,neocities
Classifier: Development Status :: 5 - Production/Stable
Classifier: License :: OSI Approved :: GNU General Public License v3 (GPLv3)
Classifier: Operating System :: OS Independent
Classifier: Framework :: Pytest
Classifier: Programming Language :: Python :: 3
Classifier: Programming Language :: Python :: 3.8
Classifier: Programming Language :: Python :: 3.9
Classifier: Programming Language :: Python :: 3.10
Classifier: Programming Language :: Python :: 3.11
Classifier: Programming Language :: Python :: 3.12
Classifier: Programming Language :: Python :: 3.13
Classifier: Programming Language :: Python :: 3 :: Only
Requires-Python: >=3.8
License-File: LICENSE
Requires-Dist: requests
Requires-Dist: treerequests
Provides-Extra: test
Requires-Dist: pytest; extra == "test"
Dynamic: license-file
